noctiluca/__init__.py
noctiluca/parallel.py
noctiluca/plot.py
noctiluca/taggedset.py
noctiluca/trajectory.py
noctiluca/analysis/__init__.py
noctiluca/analysis/p2.py
noctiluca/io/__init__.py
noctiluca/io/hdf5.py
noctiluca/io/load.py
noctiluca/io/write.py
noctiluca/util/__init__.py
noctiluca/util/_util.py
noctiluca/util/clean.py
noctiluca/util/mcmc.py
noctiluca/util/userinput.py
noctiluca-0.1.4.dist-info/METADATA
noctiluca-0.1.4.dist-info/WHEEL
noctiluca-0.1.4.dist-info/licenses/LICENSE
noctiluca-0.1.4.dist-info/RECORD
