Metadata-Version: 2.4
Name: noctiluca
Version: 0.1.4
Summary: SPT trajectory analysis
Project-URL: Homepage, https://github.com/OpenTrajectoryAnalysis/noctiluca
Project-URL: Documentation, https://noctiluca.readthedocs.io/en/latest
Project-URL: Bug Tracker, https://github.com/OpenTrajectoryAnalysis/noctiluca/issues
Author-email: Simon Grosse-Holz <sgh256@mit.edu>
License: MIT License
License-File: LICENSE
Classifier: License :: OSI Approved :: MIT License
Classifier: Operating System :: OS Independent
Classifier: Programming Language :: Python :: 3
Requires-Python: >=3.7
Requires-Dist: h5py>=2.8
Requires-Dist: numpy>=1.20
Requires-Dist: pandas>=1.2
Requires-Dist: scipy>=1.6
Requires-Dist: tqdm>=4
